tree_diet_cpp.cpython-311-x86_64-linux-gnu.so
treediet/graph_classes.py
treediet/tree_diet.py
treediet-0.3.0.dist-info/METADATA
treediet-0.3.0.dist-info/WHEEL
treediet-0.3.0.dist-info/top_level.txt
treediet-0.3.0.dist-info/RECORD
treediet-0.3.0.dist-info/licenses/LICENSE
