Metadata-Version: 2.4
Name: treediet
Version: 0.3.0
Summary: https://link.springer.com/article/10.1186/s13015-022-00213-z
Author-email: Bertrand Marchand <bertrand.marchand7@gmail.com>
Project-URL: Homepage, https://github.com/bmarchand/tree-diet
Requires-Python: >=3.9
License-File: LICENSE
Requires-Dist: numpy
Dynamic: license-file
